LICENCE
xdg_base_dirs/__init__.py
xdg_base_dirs/py.typed
xdg_base_dirs-6.0.0.dist-info/METADATA
xdg_base_dirs-6.0.0.dist-info/WHEEL
xdg_base_dirs-6.0.0.dist-info/RECORD
