Metadata-Version: 2.1
Name: xdg-base-dirs
Version: 6.0.0
Summary: Variables defined by the XDG Base Directory Specification
Home-page: https://github.com/srstevenson/xdg-base-dirs
License: ISC
Keywords: xdg,base,directory,specification
Author: Scott Stevenson
Author-email: scott@stevenson.io
Requires-Python: >=3.10,<4.0
Classifier: Development Status :: 5 - Production/Stable
Classifier: Intended Audience :: Developers
Classifier: License :: OSI Approved
Classifier: Natural Language :: English
Classifier: Operating System :: Microsoft :: Windows
Classifier: Operating System :: Unix
Classifier: Programming Language :: Python :: 3
Classifier: Programming Language :: Python :: 3.10
Classifier: Programming Language :: Python :: 3.11
Project-URL: Repository, https://github.com/srstevenson/xdg-base-dirs
